thundermail/__init__.py
thundermail/exceptions.py
thundermail/thundermail.py
thundermail-2.1.1.dist-info/LICENSE.md
thundermail-2.1.1.dist-info/METADATA
thundermail-2.1.1.dist-info/WHEEL
thundermail-2.1.1.dist-info/top_level.txt
thundermail-2.1.1.dist-info/RECORD
