Metadata-Version: 2.1
Name: thundermail
Version: 2.1.1
Summary: Thundermail Python SDK
Home-page: https://github.com/shubhojit-mitra-dev/thundermail-python-sdk/
Author: shubhojit-mitra-dev
Author-email: mitrashubhojit2005@gmail.com
License: UNKNOWN
Keywords: email,email platform
Platform: UNKNOWN
Classifier: Development Status :: 1 - Planning
Classifier: Intended Audience :: Developers
Classifier: License :: OSI Approved :: MIT License
Classifier: Natural Language :: English
Classifier: Operating System :: OS Independent
Classifier: Programming Language :: Python :: 3.7
Classifier: Programming Language :: Python :: 3.8
Classifier: Programming Language :: Python :: 3.9
Classifier: Programming Language :: Python :: 3.10
Classifier: Programming Language :: Python :: 3.11
Classifier: Programming Language :: Python :: 3.12
Requires-Python: >=3.7
License-File: LICENSE.md
Requires-Dist: requests (==2.31.0)
Requires-Dist: typing-extensions
